reloadserver/__init__.py
reloadserver/__main__.py
reloadserver-1.0.0.dist-info/LICENSE
reloadserver-1.0.0.dist-info/METADATA
reloadserver-1.0.0.dist-info/WHEEL
reloadserver-1.0.0.dist-info/entry_points.txt
reloadserver-1.0.0.dist-info/top_level.txt
reloadserver-1.0.0.dist-info/RECORD
