Metadata-Version: 2.1
Name: reloadserver
Version: 1.0.0
Summary: HTTP(S) server with automatic refresh on file changes, based on Python's http.server
Home-page: https://github.com/Densaugeo/reloadserver
Author: Densaugeo
Author-email: author@example.com
Classifier: Programming Language :: Python :: 3
Classifier: License :: OSI Approved :: MIT License
Classifier: Operating System :: OS Independent
Requires-Python: >=3.10
License-File: LICENSE
Requires-Dist: watchdog
